swagger_ui/__init__.py
swagger_ui/core.py
swagger_ui/utils.py
swagger_ui/handlers/__init__.py
swagger_ui/handlers/aiohttp.py
swagger_ui/handlers/bottle.py
swagger_ui/handlers/chalice.py
swagger_ui/handlers/falcon.py
swagger_ui/handlers/flask.py
swagger_ui/handlers/quart.py
swagger_ui/handlers/sanic.py
swagger_ui/handlers/starlette.py
swagger_ui/handlers/tornado.py
swagger_ui/static/LICENSE
swagger_ui/static/favicon-16x16.png
swagger_ui/static/favicon-32x32.png
swagger_ui/static/index.css
swagger_ui/static/oauth2-redirect.html
swagger_ui/static/swagger-editor-bundle.js
swagger_ui/static/swagger-editor-bundle.js.map
swagger_ui/static/swagger-editor-es-bundle-core.js
swagger_ui/static/swagger-editor-es-bundle-core.js.map
swagger_ui/static/swagger-editor-es-bundle.js
swagger_ui/static/swagger-editor-es-bundle.js.map
swagger_ui/static/swagger-editor-standalone-preset.js
swagger_ui/static/swagger-editor-standalone-preset.js.map
swagger_ui/static/swagger-editor.css
swagger_ui/static/swagger-editor.css.map
swagger_ui/static/swagger-editor.js
swagger_ui/static/swagger-editor.js.map
swagger_ui/static/swagger-initializer.js
swagger_ui/static/swagger-ui-bundle.js
swagger_ui/static/swagger-ui-bundle.js.map
swagger_ui/static/swagger-ui-es-bundle-core.js
swagger_ui/static/swagger-ui-es-bundle-core.js.map
swagger_ui/static/swagger-ui-es-bundle.js
swagger_ui/static/swagger-ui-es-bundle.js.map
swagger_ui/static/swagger-ui-standalone-preset.js
swagger_ui/static/swagger-ui-standalone-preset.js.map
swagger_ui/static/swagger-ui.css
swagger_ui/static/swagger-ui.css.map
swagger_ui/static/swagger-ui.js
swagger_ui/static/swagger-ui.js.map
swagger_ui/templates/doc.html
swagger_ui/templates/editor.html
test/__init__.py
test/aiohttp_test.py
test/bottle_test.py
test/chalice_test.py
test/common.py
test/conftest.py
test/falcon_test.py
test/flask_test.py
test/quart_test.py
test/sanic_test.py
test/starlette_test.py
test/tornado_test.py
swagger_ui_py-23.9.23.dist-info/LICENSE
swagger_ui_py-23.9.23.dist-info/METADATA
swagger_ui_py-23.9.23.dist-info/WHEEL
swagger_ui_py-23.9.23.dist-info/top_level.txt
swagger_ui_py-23.9.23.dist-info/RECORD
