Metadata-Version: 2.1
Name: swagger-ui-py
Version: 23.9.23
Summary: Swagger UI for Python web framework, such as Tornado, Flask, Quart, Sanic and Falcon.
Home-page: https://github.com/PWZER/swagger-ui-py
Author: PWZER
Author-email: pwzergo@gmail.com
License: Apache License 2.0
Platform: UNKNOWN
Requires-Python: >=3.0.0
License-File: LICENSE
